odoo9_addon_account_invoice_variant_configurator-9.0.1.0.0-py2.7-nspkg.pth
odoo_addons/account_invoice_variant_configurator/__openerp__.py
odoo_addons/account_invoice_variant_configurator/__init__.py
odoo_addons/account_invoice_variant_configurator/README.rst
odoo_addons/account_invoice_variant_configurator/models/__init__.py
odoo_addons/account_invoice_variant_configurator/models/account_invoice_line.py
odoo_addons/account_invoice_variant_configurator/views/account_invoice.xml
odoo_addons/account_invoice_variant_configurator/views/account_invoice_line.xml
odoo_addons/account_invoice_variant_configurator/static/description/icon.png
odoo9_addon_account_invoice_variant_configurator-9.0.1.0.0.dist-info/top_level.txt
odoo9_addon_account_invoice_variant_configurator-9.0.1.0.0.dist-info/WHEEL
odoo9_addon_account_invoice_variant_configurator-9.0.1.0.0.dist-info/RECORD
odoo9_addon_account_invoice_variant_configurator-9.0.1.0.0.dist-info/metadata.json
odoo9_addon_account_invoice_variant_configurator-9.0.1.0.0.dist-info/DESCRIPTION.rst
odoo9_addon_account_invoice_variant_configurator-9.0.1.0.0.dist-info/METADATA
odoo9_addon_account_invoice_variant_configurator-9.0.1.0.0.dist-info/namespace_packages.txt
